{"skeleton":{"hash":"f3ZYTswJefUuCRopcdO6MnE1h5w","spine":"3.8.75","x":-40,"y":-29,"width":80,"height":58},"bones":[{"name":"root"},{"name":"qiang_0000_1","parent":"root","x":32.96,"y":14.56,"scaleX":1.1123,"scaleY":1.1123},{"name":"qianghuo","parent":"root","x":35.98,"y":16.65,"scaleX":0.7212,"scaleY":0.7212},{"name":"shouqiang","parent":"root","x":-23.47,"y":-10.6},{"name":"zidanke","parent":"root","rotation":-0.03,"x":-5.81,"y":16.47}],"slots":[{"name":"qiang_0000_1","bone":"qiang_0000_1"},{"name":"qianghuo","bone":"qianghuo"},{"name":"shouqiang","bone":"shouqiang","attachment":"shouqiang"},{"name":"shouqiang2","bone":"shouqiang","blend":"screen"},{"name":"zidanke","bone":"zidanke"}],"skins":[{"name":"default","attachments":{"qianghuo":{"qianghuo":{"x":52.63,"y":4.8,"width":128,"height":97}},"qiang_0000_1":{"qiang_0001_2":{"x":23.22,"y":13.51,"width":87,"height":116},"qiang_0002_3":{"x":23.22,"y":13.51,"width":87,"height":116},"qiang_0003_4":{"x":24.31,"y":13.51,"width":87,"height":116},"qiang_0000_1":{"x":23.22,"y":13.51,"width":87,"height":116}},"zidanke":{"zidanke":{"y":0.5,"width":22,"height":21}},"shouqiang":{"shouqiang":{"x":23.47,"y":10.6,"width":80,"height":58}},"shouqiang2":{"shouqiang2":{"x":23.47,"y":10.6,"width":80,"height":58}}}}],"events":{"atk":{}},"animations":{"atk":{"slots":{"zidanke":{"color":[{"time":0.2667,"color":"ffffffff"},{"time":0.3333,"color":"ffffff00"}],"attachment":[{"time":0.0667,"name":"zidanke"}]},"shouqiang2":{"color":[{"time":0.1333,"color":"ffffffff","curve":0.25,"c3":0.75},{"time":0.2,"color":"ffffff00"}],"attachment":[{"time":0.0333,"name":"shouqiang2"}]},"qiang_0000_1":{"attachment":[{"time":0.0333,"name":"qiang_0000_1"},{"time":0.0667,"name":"qiang_0001_2"},{"time":0.1,"name":"qiang_0002_3"},{"time":0.1333,"name":"qiang_0003_4"},{"time":0.1667,"name":null}]},"qianghuo":{"attachment":[{"time":0.0667,"name":"qianghuo"},{"time":0.1667,"name":null}]}},"bones":{"qianghuo":{"scale":[{"time":0.0667},{"time":0.1667,"x":1.412,"y":1.412}]},"shouqiang":{"rotate":[{"curve":0.25,"c3":0.75},{"time":0.0667,"angle":43.21,"curve":0.25,"c3":0.75},{"time":0.3333}],"translate":[{"curve":0.25,"c3":0.75},{"time":0.0667,"x":-33.3,"y":-2.38,"curve":0.25,"c3":0.75},{"time":0.3333}]},"zidanke":{"rotate":[{"time":0.0667},{"time":0.3333,"angle":-175.77}],"translate":[{"time":0.0667,"x":-58.59,"y":1.21},{"time":0.2,"x":-65.53,"y":36.11},{"time":0.3333,"x":-75.2,"y":-20.32}]}},"events":[{"time":0.0667,"name":"atk","int":2}]}}}